sunsynk/__init__.py
sunsynk/battery.py
sunsynk/client.py
sunsynk/grid.py
sunsynk/input.py
sunsynk/inverter.py
sunsynk/output.py
sunsynk/plant.py
sunsynk/pviv.py
sunsynk/resource.py
sunsynk/version.py
sunsynk/version_info.py
sunsynk/vip.py
tests/__init__.py
tests/mock_api_server.py
tests/test_client.py
sunsynk_api_client-1.0.7.dist-info/LICENSE
sunsynk_api_client-1.0.7.dist-info/METADATA
sunsynk_api_client-1.0.7.dist-info/WHEEL
sunsynk_api_client-1.0.7.dist-info/top_level.txt
sunsynk_api_client-1.0.7.dist-info/RECORD
