Metadata-Version: 2.1
Name: sunsynk-api-client
Version: 1.0.7
Summary: API client for interacting with SunSynk APIs.
Home-page: https://github.com/jamesridgway/sunsynk-api-client
Author: James Ridgway
License: MIT
License-File: LICENSE
Requires-Dist: pylint ==2.17.5
Requires-Dist: pytest ==7.4.2
Requires-Dist: pytest-cov ==4.1.0
Requires-Dist: aiohttp ==3.9.1
Requires-Dist: vcrpy ==5.1.0
Requires-Dist: pytest-asyncio ==0.21.1
Requires-Dist: pytest-aiohttp ==1.0.5
